[
  {
    "id_partie": "Luc_1765242186",
    "joueur_nom": "Luc",
    "date_heure": "2025-12-09T01:03:06.804927+00:00",
    "theme": "mix",
    "niveau": "mix",
    "nombre_questions": 10,
    "bonnes": 7,
    "mauvaises": 3,
    "score_total": 7,
    "pourcentage": 70.0,
    "duree_seconds": 106
  },
  {
    "id_partie": "Luc_1765599980",
    "joueur_nom": "Luc",
    "date_heure": "2025-12-13T04:26:20.014889+00:00",
    "theme": "mix",
    "niveau": "mix",
    "nombre_questions": 10,
    "bonnes": 2,
    "mauvaises": 8,
    "score_total": 2,
    "pourcentage": 20.0,
    "duree_seconds": 26
  },
  {
    "id_partie": "Wesler_1765676171",
    "joueur_nom": "Wesler",
    "date_heure": "2025-12-14T01:36:11.543145+00:00",
    "theme": "Histoire",
    "niveau": "mix",
    "nombre_questions": 10,
    "bonnes": 9,
    "mauvaises": 1,
    "score_total": 9,
    "pourcentage": 90.0,
    "duree_seconds": 257
  },
  {
    "id_partie": "ewk;fd_1765690594",
    "joueur_nom": "ewk;fd",
    "date_heure": "2025-12-14T05:36:34.122605+00:00",
    "theme": "mix",
    "niveau": "mix",
    "nombre_questions": 10,
    "bonnes": 5,
    "mauvaises": 5,
    "score_total": 5,
    "pourcentage": 50.0,
    "duree_seconds": 19
  },
  {
    "id_partie": "edwsj_1765726284",
    "joueur_nom": "edwsj",
    "date_heure": "2025-12-14T15:31:24.545008+00:00",
    "theme": "mix",
    "niveau": "mix",
    "nombre_questions": 10,
    "bonnes": 2,
    "mauvaises": 8,
    "score_total": 2,
    "pourcentage": 20.0,
    "duree_seconds": 17
  },
  {
    "id_partie": "1_1765732294",
    "joueur_nom": "1",
    "date_heure": "2025-12-14T17:11:34.127042+00:00",
    "theme": "mix",
    "niveau": "mix",
    "nombre_questions": 10,
    "bonnes": 5,
    "mauvaises": 5,
    "score_total": 5,
    "pourcentage": 50.0,
    "duree_seconds": 25
  },
  {
    "id_partie": "marc_1765830912",
    "joueur_nom": "marc",
    "date_heure": "2025-12-15T20:35:12.323091+00:00",
    "theme": "mix",
    "niveau": "mix",
    "nombre_questions": 10,
    "bonnes": 6,
    "mauvaises": 4,
    "score_total": 6,
    "pourcentage": 60.0,
    "duree_seconds": 30
  },
  {
    "id_partie": "Pierre_1765834128",
    "joueur_nom": "Pierre",
    "date_heure": "2025-12-15T21:28:48.332679+00:00",
    "theme": "mix",
    "niveau": "mix",
    "nombre_questions": 10,
    "bonnes": 6,
    "mauvaises": 4,
    "score_total": 6,
    "pourcentage": 60.0,
    "duree_seconds": 241
  },
  {
    "id_partie": "Youveline_1765834609",
    "joueur_nom": "Youveline",
    "date_heure": "2025-12-15T21:36:49.211333+00:00",
    "theme": "mix",
    "niveau": "mix",
    "nombre_questions": 10,
    "bonnes": 8,
    "mauvaises": 2,
    "score_total": 8,
    "pourcentage": 80.0,
    "duree_seconds": 119
  },
  {
    "id_partie": "Maria_1766710715",
    "joueur_nom": "Maria",
    "date_heure": "2025-12-26T00:58:35.366989+00:00",
    "theme": "mix",
    "niveau": "mix",
    "nombre_questions": 10,
    "bonnes": 2,
    "mauvaises": 8,
    "temps_ecoules": 0,
    "score_total": 2,
    "pourcentage": 20.0,
    "duree_seconds": 31
  },
  {
    "id_partie": "Maria 10_1766710822",
    "joueur_nom": "Maria 10",
    "date_heure": "2025-12-26T01:00:22.814097+00:00",
    "theme": "mix",
    "niveau": "mix",
    "nombre_questions": 10,
    "bonnes": 4,
    "mauvaises": 6,
    "temps_ecoules": 0,
    "score_total": 4,
    "pourcentage": 40.0,
    "duree_seconds": 23
  },
  {
    "id_partie": "Luc 12_1766715790",
    "joueur_nom": "Luc 12",
    "date_heure": "2025-12-26T02:23:10.466657+00:00",
    "theme": "mix",
    "niveau": "mix",
    "nombre_questions": 10,
    "bonnes": 5,
    "mauvaises": 5,
    "temps_ecoules": 1,
    "score_total": 5,
    "pourcentage": 50.0,
    "duree_seconds": 113
  },
  {
    "id_partie": "mar_1766715862",
    "joueur_nom": "mar",
    "date_heure": "2025-12-26T02:24:22.837506+00:00",
    "theme": "mix",
    "niveau": "mix",
    "nombre_questions": 10,
    "bonnes": 4,
    "mauvaises": 6,
    "temps_ecoules": 0,
    "score_total": 4,
    "pourcentage": 40.0,
    "duree_seconds": 31
  },
  {
    "id_partie": "Paul_1766770030",
    "joueur_nom": "Paul",
    "date_heure": "2025-12-26T17:27:10.872947+00:00",
    "theme": "mix",
    "niveau": "mix",
    "nombre_questions": 10,
    "bonnes": 0,
    "mauvaises": 10,
    "temps_ecoules": 8,
    "score_total": 0,
    "pourcentage": 0.0,
    "duree_seconds": 186
  },
  {
    "id_partie": "Remica_1766771009",
    "joueur_nom": "Remica",
    "date_heure": "2025-12-26T17:43:29.660813+00:00",
    "theme": "mix",
    "niveau": "mix",
    "nombre_questions": 10,
    "bonnes": 0,
    "mauvaises": 10,
    "temps_ecoules": 10,
    "score_total": 0,
    "pourcentage": 0.0,
    "duree_seconds": 202
  },
  {
    "id_partie": "jhfh_1766774392",
    "joueur_nom": "jhfh",
    "date_heure": "2025-12-26T18:39:52.325231+00:00",
    "theme": "mix",
    "niveau": "mix",
    "nombre_questions": 10,
    "bonnes": 0,
    "mauvaises": 10,
    "temps_ecoules": 10,
    "score_total": 0,
    "pourcentage": 0.0,
    "duree_seconds": 202
  },
  {
    "id_partie": "ggnk_1766776526",
    "joueur_nom": "ggnk",
    "date_heure": "2025-12-26T19:15:26.095480+00:00",
    "theme": "mix",
    "niveau": "mix",
    "nombre_questions": 10,
    "bonnes": 0,
    "mauvaises": 10,
    "temps_ecoules": 10,
    "score_total": 0,
    "pourcentage": 0.0,
    "duree_seconds": 201
  },
  {
    "id_partie": "dytyd_1766781304",
    "joueur_nom": "dytyd",
    "date_heure": "2025-12-26T20:35:04.026277+00:00",
    "theme": "mix",
    "niveau": "mix",
    "nombre_questions": 10,
    "bonnes": 6,
    "mauvaises": 4,
    "temps_ecoules": 2,
    "score_total": 6,
    "pourcentage": 60.0,
    "duree_seconds": 179
  },
  {
    "id_partie": "sdjbv_1766896805",
    "joueur_nom": "sdjbv",
    "date_heure": "2025-12-28T04:40:05.753235+00:00",
    "theme": "mix",
    "niveau": "mix",
    "nombre_questions": 10,
    "bonnes": 0,
    "mauvaises": 10,
    "temps_ecoules": 10,
    "score_total": 0,
    "pourcentage": 0.0,
    "duree_seconds": 297
  },
  {
    "id_partie": "Marie_1766979931",
    "joueur_nom": "Marie",
    "date_heure": "2025-12-29T03:45:31.725274+00:00",
    "theme": "mix",
    "niveau": "mix",
    "nombre_questions": 10,
    "bonnes": 2,
    "mauvaises": 8,
    "temps_ecoules": 3,
    "score_total": 2,
    "pourcentage": 20.0,
    "duree_seconds": 194
  },
  {
    "id_partie": "Jack_1766981556",
    "joueur_nom": "Jack",
    "date_heure": "2025-12-29T04:12:36.196412+00:00",
    "theme": "mix",
    "niveau": "mix",
    "nombre_questions": 10,
    "bonnes": 7,
    "mauvaises": 3,
    "temps_ecoules": 1,
    "score_total": 7,
    "pourcentage": 70.0,
    "duree_seconds": 128
  },
  {
    "id_partie": "Jack_1766981716",
    "joueur_nom": "Jack",
    "date_heure": "2025-12-29T04:15:16.798187+00:00",
    "theme": "Culture générale",
    "niveau": "mix",
    "nombre_questions": 10,
    "bonnes": 6,
    "mauvaises": 4,
    "temps_ecoules": 0,
    "score_total": 6,
    "pourcentage": 60.0,
    "duree_seconds": 119
  },
  {
    "id_partie": "Poirreau_1767076295",
    "joueur_nom": "Poirreau",
    "date_heure": "2025-12-30T06:31:35.365486+00:00",
    "theme": "mix",
    "niveau": "mix",
    "nombre_questions": 10,
    "bonnes": 6,
    "mauvaises": 4,
    "temps_ecoules": 0,
    "score_total": 6,
    "pourcentage": 60.0,
    "duree_seconds": 59
  },
  {
    "id_partie": "Carla_1767078031",
    "joueur_nom": "Carla",
    "date_heure": "2025-12-30T07:00:31.240566+00:00",
    "theme": "mix",
    "niveau": "mix",
    "nombre_questions": 10,
    "bonnes": 8,
    "mauvaises": 2,
    "temps_ecoules": 0,
    "score_total": 8,
    "pourcentage": 80.0,
    "duree_seconds": 76
  }
]